api_easiedata/__init__.py
api_easiedata/easie_board.py
api_easiedata/easie_usertb.py
api_easiedata-0.1.4.dist-info/LICENSE
api_easiedata-0.1.4.dist-info/METADATA
api_easiedata-0.1.4.dist-info/WHEEL
api_easiedata-0.1.4.dist-info/top_level.txt
api_easiedata-0.1.4.dist-info/RECORD
