Metadata-Version: 2.1
Name: api-easiedata
Version: 0.1.4
Summary: Module to facilitate the interaction with easiedata's HTTP interface
Home-page: https://github.com/easiedata/api_easiedata
Author: The easiedata team
Author-email: barsand@easiedata.com
Classifier: Programming Language :: Python :: 3
Classifier: License :: OSI Approved :: MIT License
Classifier: Operating System :: OS Independent
Requires-Python: >= 3.6
License-File: LICENSE
Requires-Dist: requests (==2.25.1)
Requires-Dist: pandas (==1.1.5)
